[{"model": "products.location", "pk": 1, "fields": {"location_description": "Belize City", "slug": "belize-city", "created": "2018-08-08T06:00:00Z", "last_updated": "2018-08-08T06:00:00Z", "local": 1, "local_type": 3}}, {"model": "products.location", "pk": 2, "fields": {"location_description": "Belmopan City", "slug": "belmopan-city", "created": "2018-08-08T06:00:00Z", "last_updated": "2018-08-08T06:00:00Z", "local": 2, "local_type": 3}}, {"model": "products.location", "pk": 3, "fields": {"location_description": "San Pedro Town", "slug": "san-pedro-town", "created": "2018-08-08T06:00:00Z", "last_updated": "2018-08-08T06:00:00Z", "local": 3, "local_type": 4}}, {"model": "products.location", "pk": 4, "fields": {"location_description": "Orange Walk Town", "slug": "orange-walk-town", "created": "2018-08-08T06:00:00Z", "last_updated": "2018-08-08T06:00:00Z", "local": 4, "local_type": 4}}, {"model": "products.location", "pk": 5, "fields": {"location_description": "Corozal Town", "slug": "corozal-town", "created": "2018-08-08T06:00:00Z", "last_updated": "2018-08-08T06:00:00Z", "local": 5, "local_type": 4}}, {"model": "products.location", "pk": 6, "fields": {"location_description": "San Ignacio and Santa Elena Town", "slug": "san-ignacio-and-santa-elena-town", "created": "2018-08-08T06:00:00Z", "last_updated": "2018-08-08T06:00:00Z", "local": 6, "local_type": 4}}, {"model": "products.location", "pk": 7, "fields": {"location_description": "Benque Viejo Del Carmen Town", "slug": "benque-viejo-del-carmen-town", "created": "2018-08-08T06:00:00Z", "last_updated": "2018-08-08T06:00:00Z", "local": 7, "local_type": 4}}, {"model": "products.location", "pk": 8, "fields": {"location_description": "Dangriga Town", "slug": "dangriga-town", "created": "2018-08-08T06:00:00Z", "last_updated": "2018-08-08T06:00:00Z", "local": 8, "local_type": 4}}, {"model": "products.location", "pk": 9, "fields": {"location_description": "Punta Gorda", "slug": "punta-gorda", "created": "2018-08-08T06:00:00Z", "last_updated": "2018-08-08T06:00:00Z", "local": 9, "local_type": 4}}, {"model": "products.location", "pk": 10, "fields": {"location_description": "Bermudian Landing", "slug": "bermudian-landing", "created": "2018-08-08T06:00:00Z", "last_updated": "2018-08-08T06:00:00Z", "local": 10, "local_type": 5}}, {"model": "products.location", "pk": 11, "fields": {"location_description": "Biscayne", "slug": "biscayne", "created": "2018-08-08T06:00:00Z", "last_updated": "2018-08-08T06:00:00Z", "local": 11, "local_type": 5}}, {"model": "products.location", "pk": 12, "fields": {"location_description": "Bomba", "slug": "bomba", "created": "2018-08-08T06:00:00Z", "last_updated": "2018-08-08T06:00:00Z", "local": 12, "local_type": 5}}, {"model": "products.location", "pk": 13, "fields": {"location_description": "Boston", "slug": "boston", "created": "2018-08-08T06:00:00Z", "last_updated": "2018-08-08T06:00:00Z", "local": 13, "local_type": 5}}, {"model": "products.location", "pk": 14, "fields": {"location_description": "Burrell Boom", "slug": "burrell-boom", "created": "2018-08-08T06:00:00Z", "last_updated": "2018-08-08T06:00:00Z", "local": 14, "local_type": 5}}, {"model": "products.location", "pk": 15, "fields": {"location_description": "Caye Caulker", "slug": "caye-caulker", "created": "2018-08-08T06:00:00Z", "last_updated": "2018-08-08T06:00:00Z", "local": 15, "local_type": 5}}, {"model": "products.location", "pk": 16, "fields": {"location_description": "Corozalito", "slug": "corozalito", "created": "2018-08-08T06:00:00Z", "last_updated": "2018-08-08T06:00:00Z", "local": 16, "local_type": 5}}, {"model": "products.location", "pk": 17, "fields": {"location_description": "Crooked Tree", "slug": "crooked-tree", "created": "2018-08-08T06:00:00Z", "last_updated": "2018-08-08T06:00:00Z", "local": 17, "local_type": 5}}, {"model": "products.location", "pk": 18, "fields": {"location_description": "Double Head Cabbage", "slug": "double-head-cabbage", "created": "2018-08-08T06:00:00Z", "last_updated": "2018-08-08T06:00:00Z", "local": 18, "local_type": 5}}, {"model": "products.location", "pk": 19, "fields": {"location_description": "Flowers Bank", "slug": "flowers-bank", "created": "2018-08-08T06:00:00Z", "last_updated": "2018-08-08T06:00:00Z", "local": 19, "local_type": 5}}, {"model": "products.location", "pk": 20, "fields": {"location_description": "Freetown Sibun", "slug": "freetown-sibun", "created": "2018-08-08T06:00:00Z", "last_updated": "2018-08-08T06:00:00Z", "local": 20, "local_type": 5}}, {"model": "products.location", "pk": 21, "fields": {"location_description": "Gales Point", "slug": "gales-point", "created": "2018-08-08T06:00:00Z", "last_updated": "2018-08-08T06:00:00Z", "local": 21, "local_type": 5}}, {"model": "products.location", "pk": 22, "fields": {"location_description": "Gardenia", "slug": "gardenia", "created": "2018-08-08T06:00:00Z", "last_updated": "2018-08-08T06:00:00Z", "local": 22, "local_type": 5}}, {"model": "products.location", "pk": 23, "fields": {"location_description": "Gracie Rock", "slug": "gracie-rock", "created": "2018-08-08T06:00:00Z", "last_updated": "2018-08-08T06:00:00Z", "local": 23, "local_type": 5}}, {"model": "products.location", "pk": 24, "fields": {"location_description": "Hattieville", "slug": "hattieville", "created": "2018-08-08T06:00:00Z", "last_updated": "2018-08-08T06:00:00Z", "local": 24, "local_type": 5}}, {"model": "products.location", "pk": 25, "fields": {"location_description": "Isabella Bank", "slug": "isabella-bank", "created": "2018-08-08T06:00:00Z", "last_updated": "2018-08-08T06:00:00Z", "local": 25, "local_type": 5}}, {"model": "products.location", "pk": 26, "fields": {"location_description": "La Democracia", "slug": "la-democracia", "created": "2018-08-08T06:00:00Z", "last_updated": "2018-08-08T06:00:00Z", "local": 26, "local_type": 5}}, {"model": "products.location", "pk": 27, "fields": {"location_description": "Ladyville", "slug": "ladyville", "created": "2018-08-08T06:00:00Z", "last_updated": "2018-08-08T06:00:00Z", "local": 27, "local_type": 5}}, {"model": "products.location", "pk": 28, "fields": {"location_description": "Lemonal", "slug": "lemonal", "created": "2018-08-08T06:00:00Z", "last_updated": "2018-08-08T06:00:00Z", "local": 28, "local_type": 5}}, {"model": "products.location", "pk": 29, "fields": {"location_description": "Lords Bank", "slug": "lords-bank", "created": "2018-08-08T06:00:00Z", "last_updated": "2018-08-08T06:00:00Z", "local": 29, "local_type": 5}}, {"model": "products.location", "pk": 30, "fields": {"location_description": "Lucky Strike", "slug": "lucky-strike", "created": "2018-08-08T06:00:00Z", "last_updated": "2018-08-08T06:00:00Z", "local": 30, "local_type": 5}}, {"model": "products.location", "pk": 31, "fields": {"location_description": "Mahogany Heights", "slug": "mahogany-heights", "created": "2018-08-08T06:00:00Z", "last_updated": "2018-08-08T06:00:00Z", "local": 31, "local_type": 5}}, {"model": "products.location", "pk": 32, "fields": {"location_description": "Maskall", "slug": "maskall", "created": "2018-08-08T06:00:00Z", "last_updated": "2018-08-08T06:00:00Z", "local": 32, "local_type": 5}}, {"model": "products.location", "pk": 33, "fields": {"location_description": "May Pen", "slug": "may-pen", "created": "2018-08-08T06:00:00Z", "last_updated": "2018-08-08T06:00:00Z", "local": 33, "local_type": 5}}, {"model": "products.location", "pk": 34, "fields": {"location_description": "Mile 25 Village", "slug": "mile-25-village", "created": "2018-08-08T06:00:00Z", "last_updated": "2018-08-08T06:00:00Z", "local": 34, "local_type": 5}}, {"model": "products.location", "pk": 35, "fields": {"location_description": "Rancho Dolores", "slug": "rancho-dolores", "created": "2018-08-08T06:00:00Z", "last_updated": "2018-08-08T06:00:00Z", "local": 35, "local_type": 5}}, {"model": "products.location", "pk": 36, "fields": {"location_description": "Rock Stone Pond", "slug": "rock-stone-pond", "created": "2018-08-08T06:00:00Z", "last_updated": "2018-08-08T06:00:00Z", "local": 36, "local_type": 5}}, {"model": "products.location", "pk": 37, "fields": {"location_description": "Sandhill", "slug": "sandhill", "created": "2018-08-08T06:00:00Z", "last_updated": "2018-08-08T06:00:00Z", "local": 37, "local_type": 5}}, {"model": "products.location", "pk": 38, "fields": {"location_description": "Santana", "slug": "santana", "created": "2018-08-08T06:00:00Z", "last_updated": "2018-08-08T06:00:00Z", "local": 38, "local_type": 5}}, {"model": "products.location", "pk": 39, "fields": {"location_description": "Scotland Halfmoon", "slug": "scotland-halfmoon", "created": "2018-08-08T06:00:00Z", "last_updated": "2018-08-08T06:00:00Z", "local": 39, "local_type": 5}}, {"model": "products.location", "pk": 40, "fields": {"location_description": "St. Anns", "slug": "st-anns", "created": "2018-08-08T06:00:00Z", "last_updated": "2018-08-08T06:00:00Z", "local": 40, "local_type": 5}}, {"model": "products.location", "pk": 41, "fields": {"location_description": "St. Georges Caye", "slug": "st-georges-caye", "created": "2018-08-08T06:00:00Z", "last_updated": "2018-08-08T06:00:00Z", "local": 41, "local_type": 5}}, {"model": "products.location", "pk": 42, "fields": {"location_description": "St. Pauls Bank", "slug": "st-pauls-bank", "created": "2018-08-08T06:00:00Z", "last_updated": "2018-08-08T06:00:00Z", "local": 42, "local_type": 5}}, {"model": "products.location", "pk": 43, "fields": {"location_description": "Western Paradise West Lake 8 Miles", "slug": "western-paradise-west-lake-8-miles", "created": "2018-08-08T06:00:00Z", "last_updated": "2018-08-08T06:00:00Z", "local": 43, "local_type": 5}}, {"model": "products.location", "pk": 44, "fields": {"location_description": "Willows Bank", "slug": "willows-bank", "created": "2018-08-08T06:00:00Z", "last_updated": "2018-08-08T06:00:00Z", "local": 44, "local_type": 5}}, {"model": "products.location", "pk": 45, "fields": {"location_description": "Armenia", "slug": "armenia", "created": "2018-08-08T06:00:00Z", "last_updated": "2018-08-08T06:00:00Z", "local": 45, "local_type": 5}}, {"model": "products.location", "pk": 46, "fields": {"location_description": "Arenal", "slug": "arenal", "created": "2018-08-08T06:00:00Z", "last_updated": "2018-08-08T06:00:00Z", "local": 46, "local_type": 5}}, {"model": "products.location", "pk": 47, "fields": {"location_description": "Lower Barton Creek", "slug": "lower-barton-creek", "created": "2018-08-08T06:00:00Z", "last_updated": "2018-08-08T06:00:00Z", "local": 47, "local_type": 5}}, {"model": "products.location", "pk": 48, "fields": {"location_description": "Billy White", "slug": "billy-white", "created": "2018-08-08T06:00:00Z", "last_updated": "2018-08-08T06:00:00Z", "local": 48, "local_type": 5}}, {"model": "products.location", "pk": 49, "fields": {"location_description": "Blackman Eddy", "slug": "blackman-eddy", "created": "2018-08-08T06:00:00Z", "last_updated": "2018-08-08T06:00:00Z", "local": 49, "local_type": 5}}, {"model": "products.location", "pk": 50, "fields": {"location_description": "Branch Mouth", "slug": "branch-mouth", "created": "2018-08-08T06:00:00Z", "last_updated": "2018-08-08T06:00:00Z", "local": 50, "local_type": 5}}, {"model": "products.location", "pk": 51, "fields": {"location_description": "Buena Vista", "slug": "buena-vista", "created": "2018-08-08T06:00:00Z", "last_updated": "2018-08-08T06:00:00Z", "local": 51, "local_type": 5}}, {"model": "products.location", "pk": 52, "fields": {"location_description": "Bullet Tree Falls", "slug": "bullet-tree-falls", "created": "2018-08-08T06:00:00Z", "last_updated": "2018-08-08T06:00:00Z", "local": 52, "local_type": 5}}, {"model": "products.location", "pk": 53, "fields": {"location_description": "Calla Creek", "slug": "calla-creek", "created": "2018-08-08T06:00:00Z", "last_updated": "2018-08-08T06:00:00Z", "local": 53, "local_type": 5}}, {"model": "products.location", "pk": 54, "fields": {"location_description": "Camalote", "slug": "camalote", "created": "2018-08-08T06:00:00Z", "last_updated": "2018-08-08T06:00:00Z", "local": 54, "local_type": 5}}, {"model": "products.location", "pk": 55, "fields": {"location_description": "Central farm", "slug": "central-farm", "created": "2018-08-08T06:00:00Z", "last_updated": "2018-08-08T06:00:00Z", "local": 55, "local_type": 5}}, {"model": "products.location", "pk": 56, "fields": {"location_description": "Cotton Tree", "slug": "cotton-tree", "created": "2018-08-08T06:00:00Z", "last_updated": "2018-08-08T06:00:00Z", "local": 56, "local_type": 5}}, {"model": "products.location", "pk": 57, "fields": {"location_description": "Cristo Rey", "slug": "cristo-rey", "created": "2018-08-08T06:00:00Z", "last_updated": "2018-08-08T06:00:00Z", "local": 57, "local_type": 5}}, {"model": "products.location", "pk": 58, "fields": {"location_description": "Duck Run I", "slug": "duck-run-i", "created": "2018-08-08T06:00:00Z", "last_updated": "2018-08-08T06:00:00Z", "local": 58, "local_type": 5}}, {"model": "products.location", "pk": 59, "fields": {"location_description": "Duck Run II", "slug": "duck-run-ii", "created": "2018-08-08T06:00:00Z", "last_updated": "2018-08-08T06:00:00Z", "local": 59, "local_type": 5}}, {"model": "products.location", "pk": 60, "fields": {"location_description": "Duck Run III", "slug": "duck-run-iii", "created": "2018-08-08T06:00:00Z", "last_updated": "2018-08-08T06:00:00Z", "local": 60, "local_type": 5}}, {"model": "products.location", "pk": 61, "fields": {"location_description": "Esperanza", "slug": "esperanza", "created": "2018-08-08T06:00:00Z", "last_updated": "2018-08-08T06:00:00Z", "local": 61, "local_type": 5}}, {"model": "products.location", "pk": 62, "fields": {"location_description": "Franks Eddy", "slug": "franks-eddy", "created": "2018-08-08T06:00:00Z", "last_updated": "2018-08-08T06:00:00Z", "local": 62, "local_type": 5}}, {"model": "products.location", "pk": 63, "fields": {"location_description": "Georgeville", "slug": "georgeville", "created": "2018-08-08T06:00:00Z", "last_updated": "2018-08-08T06:00:00Z", "local": 63, "local_type": 5}}, {"model": "products.location", "pk": 64, "fields": {"location_description": "La Gracia", "slug": "la-gracia", "created": "2018-08-08T06:00:00Z", "last_updated": "2018-08-08T06:00:00Z", "local": 64, "local_type": 5}}, {"model": "products.location", "pk": 65, "fields": {"location_description": "Los Tambos", "slug": "los-tambos", "created": "2018-08-08T06:00:00Z", "last_updated": "2018-08-08T06:00:00Z", "local": 65, "local_type": 5}}, {"model": "products.location", "pk": 66, "fields": {"location_description": "Spanish Lookout", "slug": "spanish-lookout", "created": "2018-08-08T06:00:00Z", "last_updated": "2018-08-08T06:00:00Z", "local": 66, "local_type": 5}}, {"model": "products.location", "pk": 67, "fields": {"location_description": "Seven Miles", "slug": "seven-miles", "created": "2018-08-08T06:00:00Z", "last_updated": "2018-08-08T06:00:00Z", "local": 67, "local_type": 5}}, {"model": "products.location", "pk": 68, "fields": {"location_description": "Selena", "slug": "selena", "created": "2018-08-08T06:00:00Z", "last_updated": "2018-08-08T06:00:00Z", "local": 68, "local_type": 5}}, {"model": "products.location", "pk": 69, "fields": {"location_description": "Santa Teresita", "slug": "santa-teresita", "created": "2018-08-08T06:00:00Z", "last_updated": "2018-08-08T06:00:00Z", "local": 69, "local_type": 5}}, {"model": "products.location", "pk": 70, "fields": {"location_description": "Santa Rosa", "slug": "santa-rosa", "created": "2018-08-08T06:00:00Z", "last_updated": "2018-08-08T06:00:00Z", "local": 70, "local_type": 5}}, {"model": "products.location", "pk": 71, "fields": {"location_description": "Santa Marta", "slug": "santa-marta", "created": "2018-08-08T06:00:00Z", "last_updated": "2018-08-08T06:00:00Z", "local": 71, "local_type": 5}}, {"model": "products.location", "pk": 72, "fields": {"location_description": "Santa Familia", "slug": "santa-familia", "created": "2018-08-08T06:00:00Z", "last_updated": "2018-08-08T06:00:00Z", "local": 72, "local_type": 5}}, {"model": "products.location", "pk": 73, "fields": {"location_description": "San Marcos", "slug": "san-marcos", "created": "2018-08-08T06:00:00Z", "last_updated": "2018-08-08T06:00:00Z", "local": 73, "local_type": 5}}, {"model": "products.location", "pk": 74, "fields": {"location_description": "San Jose Succotz", "slug": "san-jose-succotz", "created": "2018-08-08T06:00:00Z", "last_updated": "2018-08-08T06:00:00Z", "local": 74, "local_type": 5}}, {"model": "products.location", "pk": 75, "fields": {"location_description": "San Antonio", "slug": "san-antonio", "created": "2018-08-08T06:00:00Z", "last_updated": "2018-08-08T06:00:00Z", "local": 75, "local_type": 5}}, {"model": "products.location", "pk": 76, "fields": {"location_description": "Ringtail Village", "slug": "ringtail-village", "created": "2018-08-08T06:00:00Z", "last_updated": "2018-08-08T06:00:00Z", "local": 76, "local_type": 5}}, {"model": "products.location", "pk": 77, "fields": {"location_description": "Roaring Creek", "slug": "roaring-creek", "created": "2018-08-08T06:00:00Z", "last_updated": "2018-08-08T06:00:00Z", "local": 77, "local_type": 5}}, {"model": "products.location", "pk": 78, "fields": {"location_description": "Paslow Falls Plant", "slug": "paslow-falls-plant", "created": "2018-08-08T06:00:00Z", "last_updated": "2018-08-08T06:00:00Z", "local": 78, "local_type": 5}}, {"model": "products.location", "pk": 79, "fields": {"location_description": "Ontario", "slug": "ontario", "created": "2018-08-08T06:00:00Z", "last_updated": "2018-08-08T06:00:00Z", "local": 79, "local_type": 5}}, {"model": "products.location", "pk": 80, "fields": {"location_description": "More Tomorrow", "slug": "more-tomorrow", "created": "2018-08-08T06:00:00Z", "last_updated": "2018-08-08T06:00:00Z", "local": 80, "local_type": 5}}, {"model": "products.location", "pk": 81, "fields": {"location_description": "Yalbac", "slug": "yalbac", "created": "2018-08-08T06:00:00Z", "last_updated": "2018-08-08T06:00:00Z", "local": 81, "local_type": 5}}, {"model": "products.location", "pk": 82, "fields": {"location_description": "Valley of Peace", "slug": "valley-of-peace", "created": "2018-08-08T06:00:00Z", "last_updated": "2018-08-08T06:00:00Z", "local": 82, "local_type": 5}}, {"model": "products.location", "pk": 83, "fields": {"location_description": "Upper Barton Creek", "slug": "upper-barton-creek", "created": "2018-08-08T06:00:00Z", "last_updated": "2018-08-08T06:00:00Z", "local": 83, "local_type": 5}}, {"model": "products.location", "pk": 84, "fields": {"location_description": "Unitedville", "slug": "unitedville", "created": "2018-08-08T06:00:00Z", "last_updated": "2018-08-08T06:00:00Z", "local": 84, "local_type": 5}}, {"model": "products.location", "pk": 85, "fields": {"location_description": "Teakettle", "slug": "teakettle", "created": "2018-08-08T06:00:00Z", "last_updated": "2018-08-08T06:00:00Z", "local": 85, "local_type": 5}}, {"model": "products.location", "pk": 86, "fields": {"location_description": "St Matthews", "slug": "st-matthews", "created": "2018-08-08T06:00:00Z", "last_updated": "2018-08-08T06:00:00Z", "local": 86, "local_type": 5}}, {"model": "products.location", "pk": 87, "fields": {"location_description": "Spring Field", "slug": "spring-field", "created": "2018-08-08T06:00:00Z", "last_updated": "2018-08-08T06:00:00Z", "local": 87, "local_type": 5}}, {"model": "products.location", "pk": 88, "fields": {"location_description": "August Pine Ridge", "slug": "august-pine-ridge", "created": "2018-08-08T06:00:00Z", "last_updated": "2018-08-08T06:00:00Z", "local": 88, "local_type": 5}}, {"model": "products.location", "pk": 89, "fields": {"location_description": "Blue Creek", "slug": "blue-creek", "created": "2018-08-08T06:00:00Z", "last_updated": "2018-08-08T06:00:00Z", "local": 89, "local_type": 5}}, {"model": "products.location", "pk": 90, "fields": {"location_description": "Carmelita", "slug": "carmelita", "created": "2018-08-08T06:00:00Z", "last_updated": "2018-08-08T06:00:00Z", "local": 90, "local_type": 5}}, {"model": "products.location", "pk": 91, "fields": {"location_description": "Chan Chich", "slug": "chan-chich", "created": "2018-08-08T06:00:00Z", "last_updated": "2018-08-08T06:00:00Z", "local": 91, "local_type": 5}}, {"model": "products.location", "pk": 92, "fields": {"location_description": "Chan Pine Ridge", "slug": "chan-pine-ridge", "created": "2018-08-08T06:00:00Z", "last_updated": "2018-08-08T06:00:00Z", "local": 92, "local_type": 5}}, {"model": "products.location", "pk": 93, "fields": {"location_description": "Cuatro Leguas", "slug": "cuatro-leguas", "created": "2018-08-08T06:00:00Z", "last_updated": "2018-08-08T06:00:00Z", "local": 93, "local_type": 5}}, {"model": "products.location", "pk": 94, "fields": {"location_description": "Douglas", "slug": "douglas", "created": "2018-08-08T06:00:00Z", "last_updated": "2018-08-08T06:00:00Z", "local": 94, "local_type": 5}}, {"model": "products.location", "pk": 95, "fields": {"location_description": "Fire Burn", "slug": "fire-burn", "created": "2018-08-08T06:00:00Z", "last_updated": "2018-08-08T06:00:00Z", "local": 95, "local_type": 5}}, {"model": "products.location", "pk": 96, "fields": {"location_description": "Guinea Grass", "slug": "guinea-grass", "created": "2018-08-08T06:00:00Z", "last_updated": "2018-08-08T06:00:00Z", "local": 96, "local_type": 5}}, {"model": "products.location", "pk": 97, "fields": {"location_description": "Honey Camp", "slug": "honey-camp", "created": "2018-08-08T06:00:00Z", "last_updated": "2018-08-08T06:00:00Z", "local": 97, "local_type": 5}}, {"model": "products.location", "pk": 98, "fields": {"location_description": "Indian Church", "slug": "indian-church", "created": "2018-08-08T06:00:00Z", "last_updated": "2018-08-08T06:00:00Z", "local": 98, "local_type": 5}}, {"model": "products.location", "pk": 99, "fields": {"location_description": "Indian Creek", "slug": "indian-creek", "created": "2018-08-08T06:00:00Z", "last_updated": "2018-08-08T06:00:00Z", "local": 99, "local_type": 5}}, {"model": "products.location", "pk": 100, "fields": {"location_description": "Indian Hill Estate", "slug": "indian-hill-estate", "created": "2018-08-08T06:00:00Z", "last_updated": "2018-08-08T06:00:00Z", "local": 100, "local_type": 5}}, {"model": "products.location", "pk": 101, "fields": {"location_description": "Petville", "slug": "petville", "created": "2018-08-08T06:00:00Z", "last_updated": "2018-08-08T06:00:00Z", "local": 101, "local_type": 5}}, {"model": "products.location", "pk": 102, "fields": {"location_description": "Richmond Hill", "slug": "richmond-hill", "created": "2018-08-08T06:00:00Z", "last_updated": "2018-08-08T06:00:00Z", "local": 102, "local_type": 5}}, {"model": "products.location", "pk": 103, "fields": {"location_description": "San Antonio", "slug": "san-antonio", "created": "2018-08-08T06:00:00Z", "last_updated": "2018-08-08T06:00:00Z", "local": 103, "local_type": 5}}, {"model": "products.location", "pk": 104, "fields": {"location_description": "San Carlos", "slug": "san-carlos", "created": "2018-08-08T06:00:00Z", "last_updated": "2018-08-08T06:00:00Z", "local": 104, "local_type": 5}}, {"model": "products.location", "pk": 105, "fields": {"location_description": "San Estevan", "slug": "san-estevan", "created": "2018-08-08T06:00:00Z", "last_updated": "2018-08-08T06:00:00Z", "local": 105, "local_type": 5}}, {"model": "products.location", "pk": 106, "fields": {"location_description": "San Felipe", "slug": "san-felipe", "created": "2018-08-08T06:00:00Z", "last_updated": "2018-08-08T06:00:00Z", "local": 106, "local_type": 5}}, {"model": "products.location", "pk": 107, "fields": {"location_description": "San Jose", "slug": "san-jose", "created": "2018-08-08T06:00:00Z", "last_updated": "2018-08-08T06:00:00Z", "local": 107, "local_type": 5}}, {"model": "products.location", "pk": 108, "fields": {"location_description": "San Jose Palmar", "slug": "san-jose-palmar", "created": "2018-08-08T06:00:00Z", "last_updated": "2018-08-08T06:00:00Z", "local": 108, "local_type": 5}}, {"model": "products.location", "pk": 109, "fields": {"location_description": "San Juan", "slug": "san-juan", "created": "2018-08-08T06:00:00Z", "last_updated": "2018-08-08T06:00:00Z", "local": 109, "local_type": 5}}, {"model": "products.location", "pk": 110, "fields": {"location_description": "San Lorenzo", "slug": "san-lorenzo", "created": "2018-08-08T06:00:00Z", "last_updated": "2018-08-08T06:00:00Z", "local": 110, "local_type": 5}}, {"model": "products.location", "pk": 111, "fields": {"location_description": "San Lazaro", "slug": "san-lazaro", "created": "2018-08-08T06:00:00Z", "last_updated": "2018-08-08T06:00:00Z", "local": 111, "local_type": 5}}, {"model": "products.location", "pk": 112, "fields": {"location_description": "San Luis", "slug": "san-luis", "created": "2018-08-08T06:00:00Z", "last_updated": "2018-08-08T06:00:00Z", "local": 112, "local_type": 5}}, {"model": "products.location", "pk": 113, "fields": {"location_description": "San Pablo", "slug": "san-pablo", "created": "2018-08-08T06:00:00Z", "last_updated": "2018-08-08T06:00:00Z", "local": 113, "local_type": 5}}, {"model": "products.location", "pk": 114, "fields": {"location_description": "San Roman", "slug": "san-roman", "created": "2018-08-08T06:00:00Z", "last_updated": "2018-08-08T06:00:00Z", "local": 114, "local_type": 5}}, {"model": "products.location", "pk": 115, "fields": {"location_description": "Santa Cruz", "slug": "santa-cruz", "created": "2018-08-08T06:00:00Z", "last_updated": "2018-08-08T06:00:00Z", "local": 115, "local_type": 5}}, {"model": "products.location", "pk": 116, "fields": {"location_description": "Santa Marta", "slug": "santa-marta", "created": "2018-08-08T06:00:00Z", "last_updated": "2018-08-08T06:00:00Z", "local": 116, "local_type": 5}}, {"model": "products.location", "pk": 117, "fields": {"location_description": "Shipyard", "slug": "shipyard", "created": "2018-08-08T06:00:00Z", "last_updated": "2018-08-08T06:00:00Z", "local": 117, "local_type": 5}}, {"model": "products.location", "pk": 118, "fields": {"location_description": "Sylvestre Camp", "slug": "sylvestre-camp", "created": "2018-08-08T06:00:00Z", "last_updated": "2018-08-08T06:00:00Z", "local": 118, "local_type": 5}}, {"model": "products.location", "pk": 119, "fields": {"location_description": "Tower Hill", "slug": "tower-hill", "created": "2018-08-08T06:00:00Z", "last_updated": "2018-08-08T06:00:00Z", "local": 119, "local_type": 5}}, {"model": "products.location", "pk": 120, "fields": {"location_description": "Tres Leguas", "slug": "tres-leguas", "created": "2018-08-08T06:00:00Z", "last_updated": "2018-08-08T06:00:00Z", "local": 120, "local_type": 5}}, {"model": "products.location", "pk": 121, "fields": {"location_description": "Trial Farm", "slug": "trial-farm", "created": "2018-08-08T06:00:00Z", "last_updated": "2018-08-08T06:00:00Z", "local": 121, "local_type": 5}}, {"model": "products.location", "pk": 122, "fields": {"location_description": "Trinidad", "slug": "trinidad", "created": "2018-08-08T06:00:00Z", "last_updated": "2018-08-08T06:00:00Z", "local": 122, "local_type": 5}}, {"model": "products.location", "pk": 123, "fields": {"location_description": "Yo Creek", "slug": "yo-creek", "created": "2018-08-08T06:00:00Z", "last_updated": "2018-08-08T06:00:00Z", "local": 123, "local_type": 5}}, {"model": "products.location", "pk": 124, "fields": {"location_description": "Altamira", "slug": "altamira", "created": "2018-08-08T06:00:00Z", "last_updated": "2018-08-08T06:00:00Z", "local": 124, "local_type": 5}}, {"model": "products.location", "pk": 125, "fields": {"location_description": "Buena Vista", "slug": "buena-vista", "created": "2018-08-08T06:00:00Z", "last_updated": "2018-08-08T06:00:00Z", "local": 125, "local_type": 5}}, {"model": "products.location", "pk": 126, "fields": {"location_description": "Calcutta", "slug": "calcutta", "created": "2018-08-08T06:00:00Z", "last_updated": "2018-08-08T06:00:00Z", "local": 126, "local_type": 5}}, {"model": "products.location", "pk": 127, "fields": {"location_description": "Caledonia", "slug": "caledonia", "created": "2018-08-08T06:00:00Z", "last_updated": "2018-08-08T06:00:00Z", "local": 127, "local_type": 5}}, {"model": "products.location", "pk": 128, "fields": {"location_description": "Carolina", "slug": "carolina", "created": "2018-08-08T06:00:00Z", "last_updated": "2018-08-08T06:00:00Z", "local": 128, "local_type": 5}}, {"model": "products.location", "pk": 129, "fields": {"location_description": "Chan Chen", "slug": "chan-chen", "created": "2018-08-08T06:00:00Z", "last_updated": "2018-08-08T06:00:00Z", "local": 129, "local_type": 5}}, {"model": "products.location", "pk": 130, "fields": {"location_description": "Chunox", "slug": "chunox", "created": "2018-08-08T06:00:00Z", "last_updated": "2018-08-08T06:00:00Z", "local": 130, "local_type": 5}}, {"model": "products.location", "pk": 131, "fields": {"location_description": "Concepcion", "slug": "concepcion", "created": "2018-08-08T06:00:00Z", "last_updated": "2018-08-08T06:00:00Z", "local": 131, "local_type": 5}}, {"model": "products.location", "pk": 132, "fields": {"location_description": "Consejo", "slug": "consejo", "created": "2018-08-08T06:00:00Z", "last_updated": "2018-08-08T06:00:00Z", "local": 132, "local_type": 5}}, {"model": "products.location", "pk": 133, "fields": {"location_description": "Copper Bank", "slug": "copper-bank", "created": "2018-08-08T06:00:00Z", "last_updated": "2018-08-08T06:00:00Z", "local": 133, "local_type": 5}}, {"model": "products.location", "pk": 134, "fields": {"location_description": "Cristo Rey", "slug": "cristo-rey", "created": "2018-08-08T06:00:00Z", "last_updated": "2018-08-08T06:00:00Z", "local": 134, "local_type": 5}}, {"model": "products.location", "pk": 135, "fields": {"location_description": "Estrella", "slug": "estrella", "created": "2018-08-08T06:00:00Z", "last_updated": "2018-08-08T06:00:00Z", "local": 135, "local_type": 5}}, {"model": "products.location", "pk": 136, "fields": {"location_description": "Libertad", "slug": "libertad", "created": "2018-08-08T06:00:00Z", "last_updated": "2018-08-08T06:00:00Z", "local": 136, "local_type": 5}}, {"model": "products.location", "pk": 137, "fields": {"location_description": "Little Belize", "slug": "little-belize", "created": "2018-08-08T06:00:00Z", "last_updated": "2018-08-08T06:00:00Z", "local": 137, "local_type": 5}}, {"model": "products.location", "pk": 138, "fields": {"location_description": "Louisville", "slug": "louisville", "created": "2018-08-08T06:00:00Z", "last_updated": "2018-08-08T06:00:00Z", "local": 138, "local_type": 5}}, {"model": "products.location", "pk": 139, "fields": {"location_description": "Paraiso", "slug": "paraiso", "created": "2018-08-08T06:00:00Z", "last_updated": "2018-08-08T06:00:00Z", "local": 139, "local_type": 5}}, {"model": "products.location", "pk": 140, "fields": {"location_description": "Patchakan", "slug": "patchakan", "created": "2018-08-08T06:00:00Z", "last_updated": "2018-08-08T06:00:00Z", "local": 140, "local_type": 5}}, {"model": "products.location", "pk": 141, "fields": {"location_description": "Progresso", "slug": "progresso", "created": "2018-08-08T06:00:00Z", "last_updated": "2018-08-08T06:00:00Z", "local": 141, "local_type": 5}}, {"model": "products.location", "pk": 142, "fields": {"location_description": "Ranchito", "slug": "ranchito", "created": "2018-08-08T06:00:00Z", "last_updated": "2018-08-08T06:00:00Z", "local": 142, "local_type": 5}}, {"model": "products.location", "pk": 143, "fields": {"location_description": "San Andres", "slug": "san-andres", "created": "2018-08-08T06:00:00Z", "last_updated": "2018-08-08T06:00:00Z", "local": 143, "local_type": 5}}, {"model": "products.location", "pk": 144, "fields": {"location_description": "San Antonio", "slug": "san-antonio", "created": "2018-08-08T06:00:00Z", "last_updated": "2018-08-08T06:00:00Z", "local": 144, "local_type": 5}}, {"model": "products.location", "pk": 145, "fields": {"location_description": "San Joaquin", "slug": "san-joaquin", "created": "2018-08-08T06:00:00Z", "last_updated": "2018-08-08T06:00:00Z", "local": 145, "local_type": 5}}, {"model": "products.location", "pk": 146, "fields": {"location_description": "San Narciso", "slug": "san-narciso", "created": "2018-08-08T06:00:00Z", "last_updated": "2018-08-08T06:00:00Z", "local": 146, "local_type": 5}}, {"model": "products.location", "pk": 147, "fields": {"location_description": "San Pedro", "slug": "san-pedro", "created": "2018-08-08T06:00:00Z", "last_updated": "2018-08-08T06:00:00Z", "local": 147, "local_type": 5}}, {"model": "products.location", "pk": 148, "fields": {"location_description": "San Roman", "slug": "san-roman", "created": "2018-08-08T06:00:00Z", "last_updated": "2018-08-08T06:00:00Z", "local": 148, "local_type": 5}}, {"model": "products.location", "pk": 149, "fields": {"location_description": "San Victor", "slug": "san-victor", "created": "2018-08-08T06:00:00Z", "last_updated": "2018-08-08T06:00:00Z", "local": 149, "local_type": 5}}, {"model": "products.location", "pk": 150, "fields": {"location_description": "Santa Clara", "slug": "santa-clara", "created": "2018-08-08T06:00:00Z", "last_updated": "2018-08-08T06:00:00Z", "local": 150, "local_type": 5}}, {"model": "products.location", "pk": 151, "fields": {"location_description": "Sarteneja", "slug": "sarteneja", "created": "2018-08-08T06:00:00Z", "last_updated": "2018-08-08T06:00:00Z", "local": 151, "local_type": 5}}, {"model": "products.location", "pk": 152, "fields": {"location_description": "Xaibe", "slug": "xaibe", "created": "2018-08-08T06:00:00Z", "last_updated": "2018-08-08T06:00:00Z", "local": 152, "local_type": 5}}, {"model": "products.location", "pk": 153, "fields": {"location_description": "Yo Chen", "slug": "yo-chen", "created": "2018-08-08T06:00:00Z", "last_updated": "2018-08-08T06:00:00Z", "local": 153, "local_type": 5}}, {"model": "products.location", "pk": 154, "fields": {"location_description": "Alta Vista", "slug": "alta-vista", "created": "2018-08-08T06:00:00Z", "last_updated": "2018-08-08T06:00:00Z", "local": 154, "local_type": 5}}, {"model": "products.location", "pk": 155, "fields": {"location_description": "Cow Pen", "slug": "cow-pen", "created": "2018-08-08T06:00:00Z", "last_updated": "2018-08-08T06:00:00Z", "local": 155, "local_type": 5}}, {"model": "products.location", "pk": 156, "fields": {"location_description": "George Town", "slug": "george-town", "created": "2018-08-08T06:00:00Z", "last_updated": "2018-08-08T06:00:00Z", "local": 156, "local_type": 5}}, {"model": "products.location", "pk": 157, "fields": {"location_description": "Hope Creek", "slug": "hope-creek", "created": "2018-08-08T06:00:00Z", "last_updated": "2018-08-08T06:00:00Z", "local": 157, "local_type": 5}}, {"model": "products.location", "pk": 158, "fields": {"location_description": "Hopkins", "slug": "hopkins", "created": "2018-08-08T06:00:00Z", "last_updated": "2018-08-08T06:00:00Z", "local": 158, "local_type": 5}}, {"model": "products.location", "pk": 159, "fields": {"location_description": "Hummingbird Community", "slug": "hummingbird-community", "created": "2018-08-08T06:00:00Z", "last_updated": "2018-08-08T06:00:00Z", "local": 159, "local_type": 5}}, {"model": "products.location", "pk": 160, "fields": {"location_description": "Independence", "slug": "independence", "created": "2018-08-08T06:00:00Z", "last_updated": "2018-08-08T06:00:00Z", "local": 160, "local_type": 5}}, {"model": "products.location", "pk": 161, "fields": {"location_description": "Kendall", "slug": "kendall", "created": "2018-08-08T06:00:00Z", "last_updated": "2018-08-08T06:00:00Z", "local": 161, "local_type": 5}}, {"model": "products.location", "pk": 162, "fields": {"location_description": "Mango Creek", "slug": "mango-creek", "created": "2018-08-08T06:00:00Z", "last_updated": "2018-08-08T06:00:00Z", "local": 162, "local_type": 5}}, {"model": "products.location", "pk": 163, "fields": {"location_description": "Maya Beach", "slug": "maya-beach", "created": "2018-08-08T06:00:00Z", "last_updated": "2018-08-08T06:00:00Z", "local": 163, "local_type": 5}}, {"model": "products.location", "pk": 164, "fields": {"location_description": "Maya Center", "slug": "maya-center", "created": "2018-08-08T06:00:00Z", "last_updated": "2018-08-08T06:00:00Z", "local": 164, "local_type": 5}}, {"model": "products.location", "pk": 165, "fields": {"location_description": "Maya Mopan", "slug": "maya-mopan", "created": "2018-08-08T06:00:00Z", "last_updated": "2018-08-08T06:00:00Z", "local": 165, "local_type": 5}}, {"model": "products.location", "pk": 166, "fields": {"location_description": "Middlesex", "slug": "middlesex", "created": "2018-08-08T06:00:00Z", "last_updated": "2018-08-08T06:00:00Z", "local": 166, "local_type": 5}}, {"model": "products.location", "pk": 167, "fields": {"location_description": "Mullins River", "slug": "mullins-river", "created": "2018-08-08T06:00:00Z", "last_updated": "2018-08-08T06:00:00Z", "local": 167, "local_type": 5}}, {"model": "products.location", "pk": 168, "fields": {"location_description": "Placencia", "slug": "placencia", "created": "2018-08-08T06:00:00Z", "last_updated": "2018-08-08T06:00:00Z", "local": 168, "local_type": 5}}, {"model": "products.location", "pk": 169, "fields": {"location_description": "Pomona", "slug": "pomona", "created": "2018-08-08T06:00:00Z", "last_updated": "2018-08-08T06:00:00Z", "local": 169, "local_type": 5}}, {"model": "products.location", "pk": 170, "fields": {"location_description": "Red Bank", "slug": "red-bank", "created": "2018-08-08T06:00:00Z", "last_updated": "2018-08-08T06:00:00Z", "local": 170, "local_type": 5}}, {"model": "products.location", "pk": 171, "fields": {"location_description": "Riversdale", "slug": "riversdale", "created": "2018-08-08T06:00:00Z", "last_updated": "2018-08-08T06:00:00Z", "local": 171, "local_type": 5}}, {"model": "products.location", "pk": 172, "fields": {"location_description": "San Juan", "slug": "san-juan", "created": "2018-08-08T06:00:00Z", "last_updated": "2018-08-08T06:00:00Z", "local": 172, "local_type": 5}}, {"model": "products.location", "pk": 173, "fields": {"location_description": "San Roman", "slug": "san-roman", "created": "2018-08-08T06:00:00Z", "last_updated": "2018-08-08T06:00:00Z", "local": 173, "local_type": 5}}, {"model": "products.location", "pk": 174, "fields": {"location_description": "Santa Cruz", "slug": "santa-cruz", "created": "2018-08-08T06:00:00Z", "last_updated": "2018-08-08T06:00:00Z", "local": 174, "local_type": 5}}, {"model": "products.location", "pk": 175, "fields": {"location_description": "Santa Rosa", "slug": "santa-rosa", "created": "2018-08-08T06:00:00Z", "last_updated": "2018-08-08T06:00:00Z", "local": 175, "local_type": 5}}, {"model": "products.location", "pk": 176, "fields": {"location_description": "Sarawee", "slug": "sarawee", "created": "2018-08-08T06:00:00Z", "last_updated": "2018-08-08T06:00:00Z", "local": 176, "local_type": 5}}, {"model": "products.location", "pk": 177, "fields": {"location_description": "Seine Bight", "slug": "seine-bight", "created": "2018-08-08T06:00:00Z", "last_updated": "2018-08-08T06:00:00Z", "local": 177, "local_type": 5}}, {"model": "products.location", "pk": 178, "fields": {"location_description": "Silk Grass", "slug": "silk-grass", "created": "2018-08-08T06:00:00Z", "last_updated": "2018-08-08T06:00:00Z", "local": 178, "local_type": 5}}, {"model": "products.location", "pk": 179, "fields": {"location_description": "Sittee River", "slug": "sittee-river", "created": "2018-08-08T06:00:00Z", "last_updated": "2018-08-08T06:00:00Z", "local": 179, "local_type": 5}}, {"model": "products.location", "pk": 180, "fields": {"location_description": "South Stann Creek", "slug": "south-stann-creek", "created": "2018-08-08T06:00:00Z", "last_updated": "2018-08-08T06:00:00Z", "local": 180, "local_type": 5}}, {"model": "products.location", "pk": 181, "fields": {"location_description": "Steadfast", "slug": "steadfast", "created": "2018-08-08T06:00:00Z", "last_updated": "2018-08-08T06:00:00Z", "local": 181, "local_type": 5}}, {"model": "products.location", "pk": 182, "fields": {"location_description": "Valley Community", "slug": "valley-community", "created": "2018-08-08T06:00:00Z", "last_updated": "2018-08-08T06:00:00Z", "local": 182, "local_type": 5}}, {"model": "products.location", "pk": 183, "fields": {"location_description": "Aguacate", "slug": "aguacate", "created": "2018-08-08T06:00:00Z", "last_updated": "2018-08-08T06:00:00Z", "local": 183, "local_type": 5}}, {"model": "products.location", "pk": 184, "fields": {"location_description": "Barranco", "slug": "barranco", "created": "2018-08-08T06:00:00Z", "last_updated": "2018-08-08T06:00:00Z", "local": 184, "local_type": 5}}, {"model": "products.location", "pk": 185, "fields": {"location_description": "Bella Vista", "slug": "bella-vista", "created": "2018-08-08T06:00:00Z", "last_updated": "2018-08-08T06:00:00Z", "local": 185, "local_type": 5}}, {"model": "products.location", "pk": 186, "fields": {"location_description": "Big Falls", "slug": "big-falls", "created": "2018-08-08T06:00:00Z", "last_updated": "2018-08-08T06:00:00Z", "local": 186, "local_type": 5}}, {"model": "products.location", "pk": 187, "fields": {"location_description": "Bladden", "slug": "bladden", "created": "2018-08-08T06:00:00Z", "last_updated": "2018-08-08T06:00:00Z", "local": 187, "local_type": 5}}, {"model": "products.location", "pk": 188, "fields": {"location_description": "Blue Creek", "slug": "blue-creek", "created": "2018-08-08T06:00:00Z", "last_updated": "2018-08-08T06:00:00Z", "local": 188, "local_type": 5}}, {"model": "products.location", "pk": 189, "fields": {"location_description": "Boom Creek", "slug": "boom-creek", "created": "2018-08-08T06:00:00Z", "last_updated": "2018-08-08T06:00:00Z", "local": 189, "local_type": 5}}, {"model": "products.location", "pk": 190, "fields": {"location_description": "Cattle Landing", "slug": "cattle-landing", "created": "2018-08-08T06:00:00Z", "last_updated": "2018-08-08T06:00:00Z", "local": 190, "local_type": 5}}, {"model": "products.location", "pk": 191, "fields": {"location_description": "Conejo", "slug": "conejo", "created": "2018-08-08T06:00:00Z", "last_updated": "2018-08-08T06:00:00Z", "local": 191, "local_type": 5}}, {"model": "products.location", "pk": 192, "fields": {"location_description": "Corazon", "slug": "corazon", "created": "2018-08-08T06:00:00Z", "last_updated": "2018-08-08T06:00:00Z", "local": 192, "local_type": 5}}, {"model": "products.location", "pk": 193, "fields": {"location_description": "Crique Jute", "slug": "crique-jute", "created": "2018-08-08T06:00:00Z", "last_updated": "2018-08-08T06:00:00Z", "local": 193, "local_type": 5}}, {"model": "products.location", "pk": 194, "fields": {"location_description": "Crique Largo", "slug": "crique-largo", "created": "2018-08-08T06:00:00Z", "last_updated": "2018-08-08T06:00:00Z", "local": 194, "local_type": 5}}, {"model": "products.location", "pk": 195, "fields": {"location_description": "Crique Sarco", "slug": "crique-sarco", "created": "2018-08-08T06:00:00Z", "last_updated": "2018-08-08T06:00:00Z", "local": 195, "local_type": 5}}, {"model": "products.location", "pk": 196, "fields": {"location_description": "Crique Trosa", "slug": "crique-trosa", "created": "2018-08-08T06:00:00Z", "last_updated": "2018-08-08T06:00:00Z", "local": 196, "local_type": 5}}, {"model": "products.location", "pk": 197, "fields": {"location_description": "Dolores", "slug": "dolores", "created": "2018-08-08T06:00:00Z", "last_updated": "2018-08-08T06:00:00Z", "local": 197, "local_type": 5}}, {"model": "products.location", "pk": 198, "fields": {"location_description": "Dump", "slug": "dump", "created": "2018-08-08T06:00:00Z", "last_updated": "2018-08-08T06:00:00Z", "local": 198, "local_type": 5}}, {"model": "products.location", "pk": 199, "fields": {"location_description": "Elridge", "slug": "elridge", "created": "2018-08-08T06:00:00Z", "last_updated": "2018-08-08T06:00:00Z", "local": 199, "local_type": 5}}, {"model": "products.location", "pk": 200, "fields": {"location_description": "Forest Home", "slug": "forest-home", "created": "2018-08-08T06:00:00Z", "last_updated": "2018-08-08T06:00:00Z", "local": 200, "local_type": 5}}, {"model": "products.location", "pk": 201, "fields": {"location_description": "Golden Stream", "slug": "golden-stream", "created": "2018-08-08T06:00:00Z", "last_updated": "2018-08-08T06:00:00Z", "local": 201, "local_type": 5}}, {"model": "products.location", "pk": 202, "fields": {"location_description": "Graham Creek", "slug": "graham-creek", "created": "2018-08-08T06:00:00Z", "last_updated": "2018-08-08T06:00:00Z", "local": 202, "local_type": 5}}, {"model": "products.location", "pk": 203, "fields": {"location_description": "Hicattee", "slug": "hicattee", "created": "2018-08-08T06:00:00Z", "last_updated": "2018-08-08T06:00:00Z", "local": 203, "local_type": 5}}, {"model": "products.location", "pk": 204, "fields": {"location_description": "Hicattee Southern Highway", "slug": "hicattee-southern-highway", "created": "2018-08-08T06:00:00Z", "last_updated": "2018-08-08T06:00:00Z", "local": 204, "local_type": 5}}, {"model": "products.location", "pk": 205, "fields": {"location_description": "Indian Creek", "slug": "indian-creek", "created": "2018-08-08T06:00:00Z", "last_updated": "2018-08-08T06:00:00Z", "local": 205, "local_type": 5}}, {"model": "products.location", "pk": 206, "fields": {"location_description": "Jacinto Westmoreland", "slug": "jacinto-westmoreland", "created": "2018-08-08T06:00:00Z", "last_updated": "2018-08-08T06:00:00Z", "local": 206, "local_type": 5}}, {"model": "products.location", "pk": 207, "fields": {"location_description": "Jalacte", "slug": "jalacte", "created": "2018-08-08T06:00:00Z", "last_updated": "2018-08-08T06:00:00Z", "local": 207, "local_type": 5}}, {"model": "products.location", "pk": 208, "fields": {"location_description": "Jordan", "slug": "jordan", "created": "2018-08-08T06:00:00Z", "last_updated": "2018-08-08T06:00:00Z", "local": 208, "local_type": 5}}, {"model": "products.location", "pk": 209, "fields": {"location_description": "Laguna", "slug": "laguna", "created": "2018-08-08T06:00:00Z", "last_updated": "2018-08-08T06:00:00Z", "local": 209, "local_type": 5}}, {"model": "products.location", "pk": 210, "fields": {"location_description": "Mabilha", "slug": "mabilha", "created": "2018-08-08T06:00:00Z", "last_updated": "2018-08-08T06:00:00Z", "local": 210, "local_type": 5}}, {"model": "products.location", "pk": 211, "fields": {"location_description": "Mafredi", "slug": "mafredi", "created": "2018-08-08T06:00:00Z", "last_updated": "2018-08-08T06:00:00Z", "local": 211, "local_type": 5}}, {"model": "products.location", "pk": 212, "fields": {"location_description": "Mango Walk", "slug": "mango-walk", "created": "2018-08-08T06:00:00Z", "last_updated": "2018-08-08T06:00:00Z", "local": 212, "local_type": 5}}, {"model": "products.location", "pk": 213, "fields": {"location_description": "Medina Bank", "slug": "medina-bank", "created": "2018-08-08T06:00:00Z", "last_updated": "2018-08-08T06:00:00Z", "local": 213, "local_type": 5}}, {"model": "products.location", "pk": 214, "fields": {"location_description": "Midway", "slug": "midway", "created": "2018-08-08T06:00:00Z", "last_updated": "2018-08-08T06:00:00Z", "local": 214, "local_type": 5}}, {"model": "products.location", "pk": 215, "fields": {"location_description": "Monkey River", "slug": "monkey-river", "created": "2018-08-08T06:00:00Z", "last_updated": "2018-08-08T06:00:00Z", "local": 215, "local_type": 5}}, {"model": "products.location", "pk": 216, "fields": {"location_description": "Moody Hill", "slug": "moody-hill", "created": "2018-08-08T06:00:00Z", "last_updated": "2018-08-08T06:00:00Z", "local": 216, "local_type": 5}}, {"model": "products.location", "pk": 217, "fields": {"location_description": "Na Luum Ca", "slug": "na-luum-ca", "created": "2018-08-08T06:00:00Z", "last_updated": "2018-08-08T06:00:00Z", "local": 217, "local_type": 5}}, {"model": "products.location", "pk": 218, "fields": {"location_description": "New Road Area", "slug": "new-road-area", "created": "2018-08-08T06:00:00Z", "last_updated": "2018-08-08T06:00:00Z", "local": 218, "local_type": 5}}, {"model": "products.location", "pk": 219, "fields": {"location_description": "Otoxha", "slug": "otoxha", "created": "2018-08-08T06:00:00Z", "last_updated": "2018-08-08T06:00:00Z", "local": 219, "local_type": 5}}, {"model": "products.location", "pk": 220, "fields": {"location_description": "Pinehill", "slug": "pinehill", "created": "2018-08-08T06:00:00Z", "last_updated": "2018-08-08T06:00:00Z", "local": 220, "local_type": 5}}, {"model": "products.location", "pk": 221, "fields": {"location_description": "Pueblo Viejo", "slug": "pueblo-viejo", "created": "2018-08-08T06:00:00Z", "last_updated": "2018-08-08T06:00:00Z", "local": 221, "local_type": 5}}, {"model": "products.location", "pk": 222, "fields": {"location_description": "Punta Negra", "slug": "punta-negra", "created": "2018-08-08T06:00:00Z", "last_updated": "2018-08-08T06:00:00Z", "local": 222, "local_type": 5}}, {"model": "products.location", "pk": 223, "fields": {"location_description": "San Antonio", "slug": "san-antonio", "created": "2018-08-08T06:00:00Z", "last_updated": "2018-08-08T06:00:00Z", "local": 223, "local_type": 5}}, {"model": "products.location", "pk": 224, "fields": {"location_description": "San Benito Poite", "slug": "san-benito-poite", "created": "2018-08-08T06:00:00Z", "last_updated": "2018-08-08T06:00:00Z", "local": 224, "local_type": 5}}, {"model": "products.location", "pk": 225, "fields": {"location_description": "San Felipe", "slug": "san-felipe", "created": "2018-08-08T06:00:00Z", "last_updated": "2018-08-08T06:00:00Z", "local": 225, "local_type": 5}}, {"model": "products.location", "pk": 226, "fields": {"location_description": "San Jose", "slug": "san-jose", "created": "2018-08-08T06:00:00Z", "last_updated": "2018-08-08T06:00:00Z", "local": 226, "local_type": 5}}, {"model": "products.location", "pk": 227, "fields": {"location_description": "San Isidro", "slug": "san-isidro", "created": "2018-08-08T06:00:00Z", "last_updated": "2018-08-08T06:00:00Z", "local": 227, "local_type": 5}}, {"model": "products.location", "pk": 228, "fields": {"location_description": "San Lucas", "slug": "san-lucas", "created": "2018-08-08T06:00:00Z", "last_updated": "2018-08-08T06:00:00Z", "local": 228, "local_type": 5}}, {"model": "products.location", "pk": 229, "fields": {"location_description": "San Marcos", "slug": "san-marcos", "created": "2018-08-08T06:00:00Z", "last_updated": "2018-08-08T06:00:00Z", "local": 229, "local_type": 5}}, {"model": "products.location", "pk": 230, "fields": {"location_description": "San Miguel", "slug": "san-miguel", "created": "2018-08-08T06:00:00Z", "last_updated": "2018-08-08T06:00:00Z", "local": 230, "local_type": 5}}, {"model": "products.location", "pk": 231, "fields": {"location_description": "San Pablo", "slug": "san-pablo", "created": "2018-08-08T06:00:00Z", "last_updated": "2018-08-08T06:00:00Z", "local": 231, "local_type": 5}}, {"model": "products.location", "pk": 232, "fields": {"location_description": "San Pedro", "slug": "san-pedro", "created": "2018-08-08T06:00:00Z", "last_updated": "2018-08-08T06:00:00Z", "local": 232, "local_type": 5}}, {"model": "products.location", "pk": 233, "fields": {"location_description": "San Vicente", "slug": "san-vicente", "created": "2018-08-08T06:00:00Z", "last_updated": "2018-08-08T06:00:00Z", "local": 233, "local_type": 5}}, {"model": "products.location", "pk": 234, "fields": {"location_description": "Santa Ana", "slug": "santa-ana", "created": "2018-08-08T06:00:00Z", "last_updated": "2018-08-08T06:00:00Z", "local": 234, "local_type": 5}}, {"model": "products.location", "pk": 235, "fields": {"location_description": "Santa Cruz", "slug": "santa-cruz", "created": "2018-08-08T06:00:00Z", "last_updated": "2018-08-08T06:00:00Z", "local": 235, "local_type": 5}}, {"model": "products.location", "pk": 236, "fields": {"location_description": "Santa Elena", "slug": "santa-elena", "created": "2018-08-08T06:00:00Z", "last_updated": "2018-08-08T06:00:00Z", "local": 236, "local_type": 5}}, {"model": "products.location", "pk": 237, "fields": {"location_description": "Santa Teresa", "slug": "santa-teresa", "created": "2018-08-08T06:00:00Z", "last_updated": "2018-08-08T06:00:00Z", "local": 237, "local_type": 5}}, {"model": "products.location", "pk": 238, "fields": {"location_description": "Silver Creek", "slug": "silver-creek", "created": "2018-08-08T06:00:00Z", "last_updated": "2018-08-08T06:00:00Z", "local": 238, "local_type": 5}}, {"model": "products.location", "pk": 239, "fields": {"location_description": "Sunday Wood", "slug": "sunday-wood", "created": "2018-08-08T06:00:00Z", "last_updated": "2018-08-08T06:00:00Z", "local": 239, "local_type": 5}}, {"model": "products.location", "pk": 240, "fields": {"location_description": "Swasey", "slug": "swasey", "created": "2018-08-08T06:00:00Z", "last_updated": "2018-08-08T06:00:00Z", "local": 240, "local_type": 5}}, {"model": "products.location", "pk": 241, "fields": {"location_description": "Tambran", "slug": "tambran", "created": "2018-08-08T06:00:00Z", "last_updated": "2018-08-08T06:00:00Z", "local": 241, "local_type": 5}}, {"model": "products.location", "pk": 242, "fields": {"location_description": "Trio", "slug": "trio", "created": "2018-08-08T06:00:00Z", "last_updated": "2018-08-08T06:00:00Z", "local": 242, "local_type": 5}}, {"model": "products.location", "pk": 243, "fields": {"location_description": "Wilson Road", "slug": "wilson-road", "created": "2018-08-08T06:00:00Z", "last_updated": "2018-08-08T06:00:00Z", "local": 243, "local_type": 5}}, {"model": "products.location", "pk": 244, "fields": {"location_description": "Yemeri Grove", "slug": "yemeri-grove", "created": "2018-08-08T06:00:00Z", "last_updated": "2018-08-08T06:00:00Z", "local": 244, "local_type": 5}}]